[
    {
        "id": "1",
        "application": {
            "date": "2023-10-11T16:26:07+03:00",
            "applicationName": "№435435"
        },
        "employeesNumber": 246,
        "assessmentTool": "Тестирование",
        "initiator": {
            "name": "Константинопольский А.А.",
            "position": "Руководитель направления",
            "initiatorID": "5b294466-56c8-11ee-85e7-00505692a567",
            "img64": "/assets/avatar.svg"
        },
        "status": "AGREED"
    },
    {
        "id": "2",
        "application": {
            "date": "2023-10-11T16:26:07+03:00",
            "applicationName": "№435436"
        },
        "employeesNumber": 250,
        "assessmentTool": "Тестирование",
        "initiator": {
            "name": "Иванов А.А.",
            "position": "Руководитель направления",
            "initiatorID": "5b294466-56c8-11ee-85e7-00505692a567",
            "img64": "/assets/avatar.svg"
        },
        "status": "ONAPPROVAL"
    },
    {
        "id": "3",
        "application": {
            "date": "2023-10-12T16:26:07+03:00",
            "applicationName": "№435436"
        },
        "employeesNumber": 27,
        "assessmentTool": "Тестирование",
        "initiator": {
            "name": "Петров А.А.",
            "position": "Руководитель направления",
            "initiatorID": "5b294466-56c8-11ee-85e7-00505692a567",
            "img64": "/assets/avatar.svg"
        },
        "status": "NOTAGREED"
    }
]